pyl2d/Filesystem.py
pyl2d/Graphics.py
pyl2d/Image.py
pyl2d/Physics.py
pyl2d/__init__.py
pyl2d/dependencies/LICENSE.FLAC.txt
pyl2d/dependencies/LICENSE.freetype.txt
pyl2d/dependencies/LICENSE.jpeg.txt
pyl2d/dependencies/LICENSE.modplug.txt
pyl2d/dependencies/LICENSE.mpg123.txt
pyl2d/dependencies/LICENSE.ogg-vorbis.txt
pyl2d/dependencies/LICENSE.png.txt
pyl2d/dependencies/LICENSE.tiff.txt
pyl2d/dependencies/LICENSE.webp.txt
pyl2d/dependencies/LICENSE.zlib.txt
pyl2d/dependencies/SDL2.dll
pyl2d/dependencies/SDL2_gfx.dll
pyl2d/dependencies/SDL2_image.dll
pyl2d/dependencies/SDL2_mixer.dll
pyl2d/dependencies/SDL2_ttf.dll
pyl2d/dependencies/libFLAC-8.dll
pyl2d/dependencies/libfreetype-6.dll
pyl2d/dependencies/libjpeg-9.dll
pyl2d/dependencies/libmodplug-1.dll
pyl2d/dependencies/libmpg123-0.dll
pyl2d/dependencies/libogg-0.dll
pyl2d/dependencies/libpng16-16.dll
pyl2d/dependencies/libtiff-5.dll
pyl2d/dependencies/libvorbis-0.dll
pyl2d/dependencies/libvorbisfile-3.dll
pyl2d/dependencies/libwebp-7.dll
pyl2d/dependencies/zlib1.dll
pyl2d/extras/__init__.py
pyl2d/extras/astar.py
pyl2d/extras/heap.py
pyl2d/fonts/GNU General Public License.txt
pyl2d/fonts/NimbusRomNo9L-Med.otf
pyl2d/fonts/NimbusRomNo9L-Med.ttf
pyl2d-0.1.4.dist-info/DESCRIPTION.rst
pyl2d-0.1.4.dist-info/METADATA
pyl2d-0.1.4.dist-info/RECORD
pyl2d-0.1.4.dist-info/WHEEL
pyl2d-0.1.4.dist-info/metadata.json
pyl2d-0.1.4.dist-info/top_level.txt
