Metadata-Version: 2.0
Name: pyl2d
Version: 0.1.4
Summary: This is a simple project to recreate love2d for python, its mostly just for personal use
Home-page: UNKNOWN
Author: Dude112113
Author-email: UNKNOWN
License: UNKNOWN
Platform: UNKNOWN
Requires-Dist: pysdl2
Requires-Dist: Box2D
Requires-Dist: fs
Requires-Dist: numpy
Requires-Dist: PyOpenGL
Requires-Dist: PyOpenGL-accelerate
Requires-Dist: Pillow
